pgcooldown/__init__.py
pgcooldown/_pgcooldown.cp312-win_amd64.pyd
pgcooldown/_pgcooldown.pyi
pgcooldown/py.typed
pgcooldown-0.3.13.dist-info/licenses/LICENSE
pgcooldown-0.3.13.dist-info/METADATA
pgcooldown-0.3.13.dist-info/WHEEL
pgcooldown-0.3.13.dist-info/top_level.txt
pgcooldown-0.3.13.dist-info/RECORD
