Metadata-Version: 2.4
Name: pgcooldown
Version: 0.3.13
Summary: A cooldown/counter class to wait for stuff in games
Author-email: Michael Lamertz <michael.lamertz@gmail.com>
License-Expression: MIT
Project-URL: homepage, https://github.com/dickerdackel/pgcooldown
Project-URL: bugtracker, https://github.com/DickerDackel/pgcooldown/issues
Project-URL: changelog, https://github.com/dickerdackel/pgcooldown/ChangeLog.md
Classifier: Development Status :: 3 - Alpha
Classifier: Intended Audience :: Developers
Classifier: Topic :: Games/Entertainment
Classifier: Topic :: Software Development :: Libraries :: pygame
License-File: LICENSE
Requires-Dist: rpeasings
Dynamic: license-file
